example_pkg/__init__.py
example_pkg/sec_example_pkg/__init__.py
example_pkg/sec_example_pkg/xiedaxia.py
xiedaxia-0.1.6.dist-info/LICENSE.txt
xiedaxia-0.1.6.dist-info/METADATA
xiedaxia-0.1.6.dist-info/WHEEL
xiedaxia-0.1.6.dist-info/top_level.txt
xiedaxia-0.1.6.dist-info/RECORD
