Metadata-Version: 2.1
Name: xiedaxia
Version: 0.1.6
Summary: 谢大侠的包
Home-page: 
Author: xanxven
Author-email: 172476115@qq.com
Classifier: Programming Language :: Python :: 3
Classifier: License :: OSI Approved :: MIT License
Classifier: Operating System :: OS Independent
Requires-Python: >=3.8
License-File: LICENSE.txt
